{
  "intro": "Hi",
  "heroPhoto": {
    "src": "../../images/lego-dummy.png",
    "alt": "My Photo"
  },
  "image": {
    "src": "../../images/waving-hand.png",
    "alt": "Waving Hand Emoji"
  },
  "title": "I'm a Tom",
  "subtitle": {
    "prefix": "I am crafting application for a ",
    "highlight": "Better World",
    "suffix": "."
  },
  "description": "This neat but beautiful website will showcase my experience in Westpac Group as my WIP placement for the Master degree in Griffith University.",
  "socialProfiles": {
    "from": ["LinkedIn", "Medium", "Github", "Mail"],
    "showIcons": false
  }
}
